<odoo noupdate="1">
    <!-- demo products for fabrication_management -->

    <!-- types of welding -->

        <record id="product_template_arc" model="product.template">
            <field name="name">Arc welding</field>
            <field name="welding">True</field>
            <field name="standard_price">50</field>
            <field name="list_price">180.0</field>
            <field name="weight">1</field>
            <field name="uom_id" ref="uom.product_uom_unit" />
            <field name="uom_po_id" ref="uom.product_uom_unit" />
        </record>
        <record id="product_template_mig" model="product.template">
            <field name="name">MIG welding</field>
            <field name="welding">True</field>
            <field name="standard_price">50</field>
            <field name="list_price">180.0</field>
            <field name="weight">1</field>
            <field name="uom_id" ref="uom.product_uom_unit" />
            <field name="uom_po_id" ref="uom.product_uom_unit" />
        </record>
        <record id="product_template_tig" model="product.template">
            <field name="name">TIG welding</field>
            <field name="welding">True</field>
            <field name="standard_price">50</field>
            <field name="list_price">180.0</field>
            <field name="weight">1</field>
            <field name="uom_id" ref="uom.product_uom_unit" />
            <field name="uom_po_id" ref="uom.product_uom_unit" />
        </record>

    <!-- types of steel used -->

        <record id="product_steel_1" model="product.product">
            <field name="name">Carbon Steel</field>
            <field name="metal">True</field>
            <field name="standard_price">50</field>
            <field name="list_price">180.0</field>
            <field name="weight">12</field>
            <field name="uom_id" ref="uom.product_uom_unit" />
            <field name="uom_po_id" ref="uom.product_uom_unit" />
        </record>

        <record id="product_steel_2" model="product.product">
            <field name="name">Alloy Steel</field>
            <field name="metal">True</field>
            <field name="standard_price">70</field>
            <field name="list_price">220.0</field>
            <field name="weight">12</field>
            <field name="uom_id" ref="uom.product_uom_unit" />
            <field name="uom_po_id" ref="uom.product_uom_unit" />
        </record>
        <record id="product_steel_3" model="product.product">
            <field name="name">Stainless Steel</field>
            <field name="metal">True</field>
            <field name="standard_price">70</field>
            <field name="list_price">160.0</field>
            <field name="weight">12</field>
            <field name="uom_id" ref="uom.product_uom_unit" />
            <field name="uom_po_id" ref="uom.product_uom_unit" />
        </record>
        <record id="product_steel_4" model="product.product">
            <field name="name">Marging Steel</field>
            <field name="metal">True</field>
            <field name="standard_price">70</field>
            <field name="list_price">200.0</field>
            <field name="weight">12</field>
            <field name="uom_id" ref="uom.product_uom_unit" />
            <field name="uom_po_id" ref="uom.product_uom_unit" />
        </record>

    <!-- welding gas products for TIG/MIG/Arc welding -->

        <record id="product_welding_gas_1" model="product.product">
            <field name="name">Argon</field>
            <field name="standard_price">70</field>
            <field name="list_price">200.0</field>
            <field name="weight">12</field>
            <field name="uom_id" ref="uom.product_uom_unit" />
            <field name="uom_po_id" ref="uom.product_uom_unit" />
        </record>
        <record id="product_welding_gas_2" model="product.product">
            <field name="name">Helium</field>
            <field name="standard_price">70</field>
            <field name="list_price">200.0</field>
            <field name="weight">12</field>
            <field name="uom_id" ref="uom.product_uom_unit" />
            <field name="uom_po_id" ref="uom.product_uom_unit" />
        </record>
        <record id="product_welding_gas_3" model="product.product">
            <field name="name">Hydrogen</field>
            <field name="standard_price">70</field>
            <field name="list_price">200.0</field>
            <field name="weight">12</field>
            <field name="uom_id" ref="uom.product_uom_unit" />
            <field name="uom_po_id" ref="uom.product_uom_unit" />
        </record>
        <record id="product_welding_gas_4" model="product.product">
            <field name="name">Carbon Dioxide</field>
            <field name="standard_price">70</field>
            <field name="list_price">200.0</field>
            <field name="weight">12</field>
            <field name="uom_id" ref="uom.product_uom_unit" />
            <field name="uom_po_id" ref="uom.product_uom_unit" />
        </record>
        <record id="product_welding_gas_5" model="product.product">
            <field name="name">Oxygen</field>
            <field name="standard_price">70</field>
            <field name="list_price">200.0</field>
            <field name="weight">12</field>
            <field name="uom_id" ref="uom.product_uom_unit" />
            <field name="uom_po_id" ref="uom.product_uom_unit" />
        </record>

    <!-- electrodes used for MIG/TIG/Arc welding -->

        <record id="product_welding_electrode_1" model="product.product">
            <field name="name">Coated Electrode</field>
            <field name="metal">True</field>
            <field name="standard_price">70</field>
            <field name="list_price">200.0</field>
            <field name="weight">12</field>
            <field name="uom_id" ref="uom.product_uom_unit" />
            <field name="uom_po_id" ref="uom.product_uom_unit" />
        </record>
        <record id="product_welding_electrode_2" model="product.product">
            <field name="name">Copper plated coil</field>
            <field name="metal">True</field>
            <field name="standard_price">70</field>
            <field name="list_price">200.0</field>
            <field name="weight">12</field>
            <field name="uom_id" ref="uom.product_uom_unit" />
            <field name="uom_po_id" ref="uom.product_uom_unit" />
        </record>
        <record id="product_welding_electrode_3" model="product.product">
            <field name="name">Thorium-Tungsten Electrode</field>
            <field name="metal">True</field>
            <field name="standard_price">70</field>
            <field name="list_price">200.0</field>
            <field name="weight">12</field>
            <field name="uom_id" ref="uom.product_uom_unit" />
            <field name="uom_po_id" ref="uom.product_uom_unit" />
        </record>

    <!-- BOM for Arc welding -->

        <record id="mrp_bom_arc_welding" model="mrp.bom">
            <field name="product_tmpl_id" ref="product_template_arc" />
            <field name="product_uom_id" ref="uom.product_uom_unit" />
        </record>
        <record id="mrp_bom_manufacture_line_arc_welding_1" model="mrp.bom.line">
            <field name="product_id" ref="product_welding_gas_1" />
            <field name="product_qty">1</field>
            <field name="product_uom_id" ref="uom.product_uom_unit" />
            <field name="bom_id" ref="mrp_bom_arc_welding" />
        </record>
        <record id="mrp_bom_manufacture_line_arc_welding_2" model="mrp.bom.line">
            <field name="product_id" ref="product_welding_electrode_1" />
            <field name="product_qty">1</field>
            <field name="product_uom_id" ref="uom.product_uom_unit" />
            <field name="bom_id" ref="mrp_bom_arc_welding" />
        </record>

    <!-- BOM for TiG welding -->

        <record id="mrp_bom_tig_welding" model="mrp.bom">
            <field name="product_tmpl_id" ref="product_template_tig" />
            <field name="product_uom_id" ref="uom.product_uom_unit" />
        </record>
        <record id="mrp_bom_manufacture_line_tig_welding_1" model="mrp.bom.line">
            <field name="product_id" ref="product_welding_gas_1" />
            <field name="product_qty">1</field>
            <field name="product_uom_id" ref="uom.product_uom_unit" />
            <field name="bom_id" ref="mrp_bom_tig_welding" />
        </record>
                <record
        id="mrp_bom_manufacture_line_tig_welding_2"
        model="mrp.bom.line"
    >
            <field name="product_id" ref="product_welding_electrode_3" />
            <field name="product_qty">1</field>
            <field name="product_uom_id" ref="uom.product_uom_unit" />
            <field name="bom_id" ref="mrp_bom_tig_welding" />
        </record>
        <record id="mrp_bom_manufacture_line_tig_welding_1" model="mrp.bom.line">
            <field name="product_id" ref="product_welding_gas_2" />
            <field name="product_qty">1</field>
            <field name="product_uom_id" ref="uom.product_uom_unit" />
            <field name="bom_id" ref="mrp_bom_tig_welding" />
        </record>

    <!-- BOM for Mig welding -->

        <record id="mrp_bom_mig_welding" model="mrp.bom">
            <field name="product_tmpl_id" ref="product_template_mig" />
            <field name="product_uom_id" ref="uom.product_uom_unit" />
        </record>
        <record id="mrp_bom_manufacture_line_mig_welding_1" model="mrp.bom.line">
            <field name="product_id" ref="product_welding_gas_1" />
            <field name="product_qty">1</field>
            <field name="product_uom_id" ref="uom.product_uom_unit" />
            <field name="bom_id" ref="mrp_bom_mig_welding" />
        </record>
        <record id="mrp_bom_manufacture_line_mig_welding_2" model="mrp.bom.line">
            <field name="product_id" ref="product_welding_electrode_2" />
            <field name="product_qty">1</field>
            <field name="product_uom_id" ref="uom.product_uom_unit" />
            <field name="bom_id" ref="mrp_bom_mig_welding" />
        </record>
        <record id="mrp_bom_manufacture_line_mig_welding_1" model="mrp.bom.line">
            <field name="product_id" ref="product_welding_gas_4" />
            <field name="product_qty">1</field>
            <field name="product_uom_id" ref="uom.product_uom_unit" />
            <field name="bom_id" ref="mrp_bom_mig_welding" />
        </record>
        <!-- vendors for the products -->
        <record id="res_partner_600" model="res.partner">
            <field name="name">Shiv Logistics</field>
            <field name="is_company">1</field>
            <field name="street">317 Fairchild Dr</field>
            <field name="city">Fairfield</field>
            <field name="zip">94535</field>
            <field name="country_id" ref="base.us" />
            <field name="email">shiv.kailash@example.com</field>
            <field name="phone">(941)-284-4875</field>
        </record>
        <record id="res_partner_601" model="res.partner">
            <field name="name">Mazda</field>
            <field name="is_company">1</field>
            <field name="street">317 Fairchild Dr</field>
            <field name="city">Fairfield</field>
            <field name="zip">94535</field>
            <field name="country_id" ref="base.us" />
            <field name="email">mazda.japani@example.com</field>
            <field name="phone">(941)-284-4875</field>
        </record>
        <record id="res_partner_603" model="res.partner">
            <field name="name">json steel</field>
            <field name="is_company">1</field>
            <field name="street">317 Fairchild Dr</field>
            <field name="city">Fairfield</field>
            <field name="zip">94535</field>
            <field name="country_id" ref="base.us" />
            <field name="email">json.steel@example.com</field>
            <field name="phone">(941)-284-4875</field>
        </record>
        <record id="res_partner_605" model="res.partner">
            <field name="name">Phantech Welding Rods</field>
            <field name="is_company">1</field>
            <field name="street">317 Fairchild Dr</field>
            <field name="city">Fairfield</field>
            <field name="zip">94535</field>
            <field name="country_id" ref="base.us" />
            <field name="email">json.steel@example.com</field>
            <field name="phone">(941)-284-4875</field>
        </record>
        <record id="res_partner_606" model="res.partner">
            <field name="name">Bhopal Gas Company</field>
            <field name="is_company">1</field>
            <field name="street">317 Fairchild Dr</field>
            <field name="city">Fairfield</field>
            <field name="zip">94535</field>
            <field name="country_id" ref="base.us" />
            <field name="email">json.steel@example.com</field>
            <field name="phone">(941)-284-4875</field>
        </record>

        <!-- product supplier info: -->

        <!-- steel supplier -->
        <record id="product_supplierinfo_steel_1" model="product.supplierinfo">
            <field name="product_id" ref="product_steel_1" />
            <field name="name" ref="fabrication_management.res_partner_603" />
            <field name="delay">3</field>
            <field name="min_qty">1</field>
            <field name="price">750</field>
            <field name="currency_id" ref="base.USD" />
        </record>
        <record id="product_supplierinfo_steel_2" model="product.supplierinfo">
            <field name="product_id" ref="product_steel_2" />
            <field name="name" ref="fabrication_management.res_partner_603" />
            <field name="delay">3</field>
            <field name="min_qty">1</field>
            <field name="price">750</field>
            <field name="currency_id" ref="base.USD" />
        </record>
        <record id="product_supplierinfo_steel_3" model="product.supplierinfo">
            <field name="product_id" ref="product_steel_3" />
            <field name="name" ref="fabrication_management.res_partner_603" />
            <field name="delay">3</field>
            <field name="min_qty">1</field>
            <field name="price">750</field>
            <field name="currency_id" ref="base.USD" />
        </record>
        <record id="product_supplierinfo_steel_4" model="product.supplierinfo">
            <field name="product_id" ref="product_steel_4" />
            <field name="name" ref="fabrication_management.res_partner_603" />
            <field name="delay">3</field>
            <field name="min_qty">1</field>
            <field name="price">750</field>
            <field name="currency_id" ref="base.USD" />
        </record>

        <!-- gas supplier -->
        <record id="product_supplierinfo_gas_1" model="product.supplierinfo">
            <field name="product_id" ref="product_welding_gas_1" />
            <field name="name" ref="fabrication_management.res_partner_606" />
            <field name="delay">3</field>
            <field name="min_qty">1</field>
            <field name="price">750</field>
            <field name="currency_id" ref="base.USD" />
        </record>
                <record id="product_supplierinfo_gas_2" model="product.supplierinfo">
            <field name="product_id" ref="product_welding_gas_2" />
            <field name="name" ref="fabrication_management.res_partner_606" />
            <field name="delay">3</field>
            <field name="min_qty">1</field>
            <field name="price">750</field>
            <field name="currency_id" ref="base.USD" />
        </record>
                <record id="product_supplierinfo_gas_3" model="product.supplierinfo">
            <field name="product_id" ref="product_welding_gas_3" />
            <field name="name" ref="fabrication_management.res_partner_606" />
            <field name="delay">3</field>
            <field name="min_qty">1</field>
            <field name="price">750</field>
            <field name="currency_id" ref="base.USD" />
        </record>
                <record id="product_supplierinfo_gas_4" model="product.supplierinfo">
            <field name="product_id" ref="product_welding_gas_4" />
            <field name="name" ref="fabrication_management.res_partner_606" />
            <field name="delay">3</field>
            <field name="min_qty">1</field>
            <field name="price">750</field>
            <field name="currency_id" ref="base.USD" />
        </record>
                <record id="product_supplierinfo_gas_5" model="product.supplierinfo">
            <field name="product_id" ref="product_welding_gas_5" />
            <field name="name" ref="fabrication_management.res_partner_606" />
            <field name="delay">3</field>
            <field name="min_qty">1</field>
            <field name="price">750</field>
            <field name="currency_id" ref="base.USD" />
        </record>

        <!-- electrode supplier -->
        <record id="product_supplierinfo_electrode_1" model="product.supplierinfo">
            <field name="product_id" ref="product_welding_electrode_1" />
            <field name="name" ref="fabrication_management.res_partner_601" />
            <field name="delay">3</field>
            <field name="min_qty">1</field>
            <field name="price">750</field>
            <field name="currency_id" ref="base.USD" />
        </record>
        <record id="product_supplierinfo_electrode_2" model="product.supplierinfo">
            <field name="product_id" ref="product_welding_electrode_2" />
            <field name="name" ref="fabrication_management.res_partner_601" />
            <field name="delay">3</field>
            <field name="min_qty">1</field>
            <field name="price">750</field>
            <field name="currency_id" ref="base.USD" />
        </record>
        <record id="product_supplierinfo_electrode_3" model="product.supplierinfo">
            <field name="product_id" ref="product_welding_electrode_3" />
            <field name="name" ref="fabrication_management.res_partner_601" />
            <field name="delay">3</field>
            <field name="min_qty">1</field>
            <field name="price">750</field>
            <field name="currency_id" ref="base.USD" />
        </record>

<!-- final Products with BoM -->

    <!-- warehouse shed -->
        <record id="product_final_shed" model="product.template">
            <field name="name">Industrial Shed</field>
        <field name="standard_price">50</field>
            <field name="list_price">18000.0</field>
            <field name="weight">1</field>
            <field name="uom_id" ref="uom.product_uom_unit" />
            <field name="uom_po_id" ref="uom.product_uom_unit" />
        </record>
        <!-- BOM -->
        <record id="mrp_bom_shed" model="mrp.bom">
            <field name="product_tmpl_id" ref="product_final_shed" />
            <field name="product_uom_id" ref="uom.product_uom_unit" />
        </record>
            <record id="mrp_bom_manufacture_line_shed_1" model="mrp.bom.line">
            <field name="product_id" ref="product_steel_2" />
            <field name="product_qty">3</field>
            <field name="product_uom_id" ref="uom.product_uom_unit" />
            <field name="bom_id" ref="mrp_bom_shed" />
        </record>
        <record id="mrp_bom_manufacture_line_shed_2" model="mrp.bom.line">
            <field name="product_id" ref="product_welding_electrode_1" />
            <field name="product_qty">4</field>
            <field name="product_uom_id" ref="uom.product_uom_unit" />
            <field name="bom_id" ref="mrp_bom_shed" />
        </record>
        <record id="mrp_bom_manufacture_line_shed_3" model="mrp.bom.line">
            <field name="product_id" ref="product_welding_gas_5" />
            <field name="product_qty">5</field>
            <field name="product_uom_id" ref="uom.product_uom_unit" />
            <field name="bom_id" ref="mrp_bom_shed" />
        </record>

    <!-- High Pressure Vessle -->
        <record id="product_final_hpv" model="product.template">
                <field name="name">High Pressure Vessle</field>
                <field name="standard_price">50</field>
                <field name="list_price">24000.0</field>
                <field name="weight">1</field>
                <field name="uom_id" ref="uom.product_uom_unit" />
                <field name="uom_po_id" ref="uom.product_uom_unit" />
            </record>
            <!-- BOM -->
            <record id="mrp_bom_hpv" model="mrp.bom">
                <field name="product_tmpl_id" ref="product_final_hpv" />
                <field name="product_uom_id" ref="uom.product_uom_unit" />
            </record>
                <record id="mrp_bom_manufacture_line_hpv_1" model="mrp.bom.line">
                <field name="product_id" ref="product_steel_1" />
                <field name="product_qty">3</field>
                <field name="product_uom_id" ref="uom.product_uom_unit" />
                <field name="bom_id" ref="mrp_bom_hpv" />
            </record>
            <record id="mrp_bom_manufacture_line_hpv_2" model="mrp.bom.line">
                <field name="product_id" ref="product_welding_electrode_3" />
                <field name="product_qty">4</field>
                <field name="product_uom_id" ref="uom.product_uom_unit" />
                <field name="bom_id" ref="mrp_bom_hpv" />
            </record>
            <record id="mrp_bom_manufacture_line_hpv_3" model="mrp.bom.line">
                <field name="product_id" ref="product_welding_gas_4" />
                <field name="product_qty">5</field>
                <field name="product_uom_id" ref="uom.product_uom_unit" />
                <field name="bom_id" ref="mrp_bom_hpv" />
            </record>
        <!-- Boiler -->
        <record id="product_final_boiler" model="product.template">
                <field name="name">Boiler</field>
                <field name="standard_price">50</field>
                <field name="list_price">24000.0</field>
                <field name="weight">1</field>
                <field name="uom_id" ref="uom.product_uom_unit" />
                <field name="uom_po_id" ref="uom.product_uom_unit" />
            </record>
            <!-- BOM -->
            <record id="mrp_bom_boiler" model="mrp.bom">
                <field name="product_tmpl_id" ref="product_final_boiler" />
                <field name="product_uom_id" ref="uom.product_uom_unit" />
            </record>
                <record id="mrp_bom_manufacture_line_boiler_1" model="mrp.bom.line">
                <field name="product_id" ref="product_steel_3" />
                <field name="product_qty">3</field>
                <field name="product_uom_id" ref="uom.product_uom_unit" />
                <field name="bom_id" ref="mrp_bom_boiler" />
            </record>
            <record id="mrp_bom_manufacture_line_boiler_2" model="mrp.bom.line">
                <field name="product_id" ref="product_welding_electrode_1" />
                <field name="product_qty">4</field>
                <field name="product_uom_id" ref="uom.product_uom_unit" />
                <field name="bom_id" ref="mrp_bom_boiler" />
            </record>
            <record id="mrp_bom_manufacture_line_boiler_3" model="mrp.bom.line">
                <field name="product_id" ref="product_welding_gas_2" />
                <field name="product_qty">5</field>
                <field name="product_uom_id" ref="uom.product_uom_unit" />
                <field name="bom_id" ref="mrp_bom_boiler" />
            </record>

        <!-- High Pressure Vessle Support -->
        <record id="product_final_hpvs" model="product.template">
                <field name="name">High Pressure Vessle Support</field>
                <field name="standard_price">50</field>
                <field name="list_price">24000.0</field>
                <field name="weight">1</field>
                <field name="uom_id" ref="uom.product_uom_unit" />
                <field name="uom_po_id" ref="uom.product_uom_unit" />
            </record>
            <!-- BOM -->
            <record id="mrp_bom_hpvs" model="mrp.bom">
                <field name="product_tmpl_id" ref="product_final_hpvs" />
                <field name="product_uom_id" ref="uom.product_uom_unit" />
            </record>
                <record id="mrp_bom_manufacture_line_hpvs_1" model="mrp.bom.line">
                <field name="product_id" ref="product_steel_2" />
                <field name="product_qty">3</field>
                <field name="product_uom_id" ref="uom.product_uom_unit" />
                <field name="bom_id" ref="mrp_bom_hpvs" />
            </record>
            <record id="mrp_bom_manufacture_line_hpvs_2" model="mrp.bom.line">
                <field name="product_id" ref="product_welding_electrode_2" />
                <field name="product_qty">4</field>
                <field name="product_uom_id" ref="uom.product_uom_unit" />
                <field name="bom_id" ref="mrp_bom_hpvs" />
            </record>
            <record id="mrp_bom_manufacture_line_hpvs_3" model="mrp.bom.line">
                <field name="product_id" ref="product_welding_gas_1" />
                <field name="product_qty">5</field>
                <field name="product_uom_id" ref="uom.product_uom_unit" />
                <field name="bom_id" ref="mrp_bom_hpvs" />
            </record>
</odoo>
